dgg_chat/__init__.py
dgg_chat/_dgg_chat.py
dgg_chat/_event_types.py
dgg_chat/_handler.py
dgg_chat/_utils.py
dgg_chat/api/__init__.py
dgg_chat/api/_api.py
dgg_chat/api/_private_message.py
dgg_chat/api/_stream_info.py
dgg_chat/api/_user.py
dgg_chat/cdn/__init__.py
dgg_chat/cdn/_cdn.py
dgg_chat/exceptions/__init__.py
dgg_chat/exceptions/_exceptions.py
dgg_chat/logging/__init__.py
dgg_chat/logging/_logging.py
dgg_chat/messages/__init__.py
dgg_chat/messages/_messages.py
dgg_chat/overrustle_logs/__init__.py
dgg_chat/overrustle_logs/_chat_message.py
dgg_chat/overrustle_logs/_logs.py
dgg_chat-0.1.9a0.dist-info/LICENSE
dgg_chat-0.1.9a0.dist-info/METADATA
dgg_chat-0.1.9a0.dist-info/WHEEL
dgg_chat-0.1.9a0.dist-info/top_level.txt
dgg_chat-0.1.9a0.dist-info/RECORD
