Metadata-Version: 2.1
Name: dgg-chat
Version: 0.1.9a0
Summary: A package that lets you do stuff in dgg chat
Home-page: https://github.com/gabrieljablonski/dgg-chat
Author: Gabriel Jablonski
Author-email: contact@gabrieljablonski.com
License: MIT
Keywords: chat-bot,chat,destinygg,dgg
Platform: UNKNOWN
Classifier: Development Status :: 3 - Alpha
Classifier: Intended Audience :: Developers
Classifier: License :: OSI Approved :: MIT License
Classifier: Programming Language :: Python :: 3.8
Requires-Python: >=3.8
Requires-Dist: websocket-client
Requires-Dist: requests
Requires-Dist: numpy
Requires-Dist: wsaccel
